keyvalues3/__init__.py
keyvalues3/binaryreader.py
keyvalues3/binarywriter.py
keyvalues3/keyvalues3.py
keyvalues3/kv3file.py
keyvalues3/textreader.py
keyvalues3/textwriter.py
keyvalues3/utils/__init__.py
keyvalues3/utils/buffer.py
keyvalues3/utils/compression.py
keyvalues3/utils/helpers.py
keyvalues3-0.5.dist-info/licenses/LICENSE
keyvalues3-0.5.dist-info/WHEEL
keyvalues3-0.5.dist-info/METADATA
keyvalues3-0.5.dist-info/RECORD
