Metadata-Version: 2.4
Name: keyvalues3
Version: 0.5
Summary: Read and write Valve's KeyValues3 format
Keywords: parser,kv3,keyvalues,keyvalues3,valve
Author-email: kristiker <kristik06@outlook.com>
Requires-Python: >=3.12
License-File: LICENSE
Requires-Dist: parsimonious >=0.10,<1.0
Requires-Dist: lz4 >=4.3.2,<5.0
Requires-Dist: zstandard >=0.24
Requires-Dist: pytest ==7.2.2 ; extra == "test"
Project-URL: Source, https://github.com/kristiker/keyvalues3
Provides-Extra: test
